README.md
setup.py
chd_login/__init__.py
chd_login/client.py
chd_login/encrypt.py
chd_login.egg-info/PKG-INFO
chd_login.egg-info/SOURCES.txt
chd_login.egg-info/dependency_links.txt
chd_login.egg-info/requires.txt
chd_login.egg-info/top_level.txt