Metadata-Version: 2.1
Name: chd-login
Version: 0.0.9
Summary: A Login Tool for CHD
Home-page: https://www.oren.ink/
Author: Oren Zhang
Author-email: oren_zhang@outlook.com
License: UNKNOWN
Platform: UNKNOWN
